panels/__init__.py
panels/_version.py
panels/json/about.json
panels/json/affiliations-index-pattern.json
panels/json/affiliations.json
panels/json/all_enriched-index-pattern.json
panels/json/all_enriched_tickets-index-pattern.json
panels/json/all_onion-index-pattern.json
panels/json/apache-index-pattern.json
panels/json/apache.json
panels/json/askbot-index-pattern.json
panels/json/askbot.json
panels/json/attracted-contributors.json
panels/json/bugzilla-index-pattern.json
panels/json/bugzilla.json
panels/json/bugzilla_backlog.json
panels/json/bugzilla_timing.json
panels/json/cocom-index-pattern.json
panels/json/cocom.json
panels/json/cocom_study-index-pattern.json
panels/json/colic-index-pattern.json
panels/json/colic.json
panels/json/colic_study-index-pattern.json
panels/json/confluence-index-pattern.json
panels/json/confluence.json
panels/json/contributors_growth.json
panels/json/data_status.json
panels/json/demographics-index-pattern.json
panels/json/demographics.json
panels/json/demographics_contribution-index-pattern.json
panels/json/discourse-index-pattern.json
panels/json/discourse.json
panels/json/discourse_devrel.json
panels/json/docker.json
panels/json/docker_deps-index-pattern.json
panels/json/docker_smells-index-pattern.json
panels/json/dockerhub-index-pattern.json
panels/json/dockerhub.json
panels/json/emtech/adoption/crates-emergintech-index-pattern.json
panels/json/emtech/adoption/emerging_tech_adoption.json
panels/json/emtech/adoption/emerging_tech_adoption_no_crates.json
panels/json/emtech/adoption/github_issues-index-pattern.json
panels/json/emtech/dev/emerging_tech_dev.json
panels/json/emtech/dev/git-emergingtech-index-pattern.json
panels/json/emtech/dev/git_areas_of_code-index-pattern.json
panels/json/emtech/dev/github-emergingtech-index-pattern.json
panels/json/emtech/social/emerging_tech_social.json
panels/json/emtech/social/irc-emergingtech-index-pattern.json
panels/json/emtech/social/meetup-emergingtech-index-pattern.json
grimoirelab_panels-1.2.0.dist-info/METADATA
grimoirelab_panels-1.2.0.dist-info/WHEEL
grimoirelab_panels-1.2.0.dist-info/licenses/AUTHORS
grimoirelab_panels-1.2.0.dist-info/licenses/LICENSE
grimoirelab_panels-1.2.0.dist-info/RECORD
